{
  "version": "7",
  "dialect": "sqlite",
  "entries": [
    {
      "idx": 0,
      "version": "6",
      "when": 1780669083959,
      "tag": "0000_glossy_power_pack",
      "breakpoints": true
    },
    {
      "idx": 1,
      "version": "6",
      "when": 1780669200000,
      "tag": "0001_wide_priority",
      "breakpoints": true
    },
    {
      "idx": 2,
      "version": "6",
      "when": 1780759731503,
      "tag": "0002_myday_tags",
      "breakpoints": true
    },
    {
      "idx": 3,
      "version": "6",
      "when": 1781193600000,
      "tag": "0003_add_contact_notes",
      "breakpoints": true
    },
    {
      "idx": 4,
      "version": "6",
      "when": 1781193600000,
      "tag": "0004_add_contact_tags",
      "breakpoints": true
    },
    {
      "idx": 5,
      "version": "6",
      "when": 1781193600000,
      "tag": "0005_custom_tags",
      "breakpoints": true
    },
    {
      "idx": 6,
      "version": "6",
      "when": 1782000000000,
      "tag": "0006_settings",
      "breakpoints": true
    }
  ]
}
